dynamic_storage/__init__.py
dynamic_storage/models.py
dynamic_storage/signals.py
dynamic_storage/storage.py
dynamic_storage/test/storage.py
django_dynamic_storage-1.0.0.dist-info/METADATA
django_dynamic_storage-1.0.0.dist-info/WHEEL
django_dynamic_storage-1.0.0.dist-info/RECORD
