Metadata-Version: 2.1
Name: django-dynamic-storage
Version: 1.0.0
Summary: Use and choose storages at runtime based on your logic for each model FileField instance separately.
Home-page: https://github.com/engAmirEng/django-dynamic-storage
License: Apache-2.0
Keywords: django,django-storages,djangostorage
Author: Amir Khalife
Author-email: eng.amir.bu@gmail.com
Requires-Python: >=3.7,<3.12
Classifier: Framework :: Django
Classifier: Framework :: Django :: 2.2
Classifier: Framework :: Django :: 3.0
Classifier: Framework :: Django :: 3.1
Classifier: Framework :: Django :: 3.2
Classifier: Framework :: Django :: 4.0
Classifier: Framework :: Django :: 4.1
Classifier: Framework :: Django :: 4.2
Classifier: Framework :: Django :: 5.0
Classifier: License :: OSI Approved :: Apache Software License
Classifier: Programming Language :: Python :: 3
Classifier: Programming Language :: Python :: 3.7
Classifier: Programming Language :: Python :: 3.8
Classifier: Programming Language :: Python :: 3.9
Classifier: Programming Language :: Python :: 3.10
Classifier: Programming Language :: Python :: 3.11
Requires-Dist: Django (>=2.2,<5.1)
Project-URL: Repository, https://github.com/engAmirEng/django-dynamic-storage
